airtouch4pyapi/__init__.py
airtouch4pyapi/airtouch.py
airtouch4pyapi/communicate.py
airtouch4pyapi/helper.py
airtouch4pyapi/packetmap.py
airtouch4pyapi-1.0.8.dist-info/LICENSE
airtouch4pyapi-1.0.8.dist-info/METADATA
airtouch4pyapi-1.0.8.dist-info/WHEEL
airtouch4pyapi-1.0.8.dist-info/top_level.txt
airtouch4pyapi-1.0.8.dist-info/RECORD
