Metadata-Version: 2.1
Name: airtouch4pyapi
Version: 1.0.8
Summary: An api allowing control of AC state (temperature, on/off, mode) of an Airtouch 4 controller locally over TCP
Home-page: https://github.com/LonePurpleWolf/airtouch4pyapi
Author: Sam Sinnamon
Author-email: samsinnamon@hotmail.com
Classifier: Programming Language :: Python :: 3
Classifier: License :: OSI Approved :: MIT License
Classifier: Operating System :: OS Independent
Requires-Python: >=3.6
License-File: LICENSE
Requires-Dist: numpy
